youtube_thubmnail_extractor/__init__.py
youtube_thubmnail_extractor/extractor.py
youtube_thumbnail_extractor-0.1.3.dist-info/LICENSE
youtube_thumbnail_extractor-0.1.3.dist-info/METADATA
youtube_thumbnail_extractor-0.1.3.dist-info/WHEEL
youtube_thumbnail_extractor-0.1.3.dist-info/top_level.txt
youtube_thumbnail_extractor-0.1.3.dist-info/RECORD
